openfst_python/__init__.py
openfst_python/libfst-956dbf92.so.17
openfst_python/libfstfar-e452bd0f.so.17
openfst_python/libfstfarscript-27ce774b.so.17
openfst_python/libfstscript-7da49e8b.so.17
openfst_python/pywrapfst.cpython-36m-x86_64-linux-gnu.so
openfst_python/pywrapfst.py
openfst_python/test.py
openfst_python-1.7.3.dist-info/LICENSE
openfst_python-1.7.3.dist-info/METADATA
openfst_python-1.7.3.dist-info/WHEEL
openfst_python-1.7.3.dist-info/top_level.txt
openfst_python-1.7.3.dist-info/RECORD
